my_package/__init__.py
my_package/database.py
my_package/model.py
my_package/todocli.py
smriti_todo_cli-0.1.dist-info/LICENSE.txt
smriti_todo_cli-0.1.dist-info/METADATA
smriti_todo_cli-0.1.dist-info/WHEEL
smriti_todo_cli-0.1.dist-info/top_level.txt
smriti_todo_cli-0.1.dist-info/RECORD
